neuro_airflow_plugin/__init__.py
neuro_airflow_plugin/asyncio_tools.py
neuro_airflow_plugin/hook.py
neuro_airflow_plugin/neuro_plugin.py
neuro_airflow_plugin/operator.py
neuro_airflow_plugin/sensor.py
neuro_airflow_plugin-0.0.1.dist-info/LICENSE.txt
neuro_airflow_plugin-0.0.1.dist-info/METADATA
neuro_airflow_plugin-0.0.1.dist-info/WHEEL
neuro_airflow_plugin-0.0.1.dist-info/entry_points.txt
neuro_airflow_plugin-0.0.1.dist-info/top_level.txt
neuro_airflow_plugin-0.0.1.dist-info/RECORD
