Metadata-Version: 2.1
Name: neuro-airflow-plugin
Version: 0.0.1
Summary: Neu.ro Airflow plugin
Home-page: https://github.com/neuromation/platform-airflow-plugin
Author: Neu.ro Team
Author-email: team@neu.ro
License: Apache License, version 2.0
Platform: UNKNOWN
Classifier: Programming Language :: Python :: 3
Classifier: License :: Other/Proprietary License
Classifier: Operating System :: OS Independent
Classifier: Development Status :: 4 - Beta
Classifier: Environment :: Plugins
Classifier: Intended Audience :: Developers
Classifier: Intended Audience :: Science/Research
Classifier: Intended Audience :: Information Technology
Classifier: Topic :: Scientific/Engineering :: Artificial Intelligence
Classifier: Topic :: Software Development
Classifier: Topic :: Utilities
Classifier: License :: OSI Approved :: Apache Software License
Requires-Python: >=3.7
Requires-Dist: apache-airflow (<2.0.0)
Requires-Dist: neuromation (>=20.4.6)
Requires-Dist: typing-extensions (>=3.7.4)
